
  { "token" : "count",
    "instances" : 
    [ 
      { "docId" : "howDoIUseIt",
        "docUri" : "howDoIUseIt.html",
        "score" : 3,
        "contexts" : 
        [ 
          { "form" : "count",
            "context" : "...documents in the search results based on their word-<mark>count<\/mark>: Users would then be able to set...",
            "weight" : 1,
            "pos" : 261 },
          
          { "form" : "count\"",
            "context" : "<meta name=\"Word-<mark>count\"<\/mark>  class=\"staticSearch.num\" content=\"2193\"\/>",
            "weight" : 1,
            "pos" : 266 },
          
          { "form" : "count",
            "context" : "...be able to set a minimum and\/or maximum word-<mark>count<\/mark> when searching for documents.",
            "weight" : 1,
            "pos" : 280 } ] } ] }