
  { "token" : "param",
    "instances" : 
    [ 
      { "docId" : "schemaSpec",
        "docUri" : "schemaSpec.html",
        "score" : 18,
        "contexts" : 
        [ 
          { "form" : "params",
            "context" : "Appendix A.1.13 <<mark>params<\/mark>>",
            "weight" : 2,
            "pos" : 501 },
          
          { "form" : "params",
            "context" : "ss: contexts excludes <mark>params<\/mark> rules",
            "weight" : 1,
            "pos" : 33 },
          
          { "form" : "params",
            "context" : "ss: <mark>params<\/mark>",
            "weight" : 1,
            "pos" : 159 },
          
          { "form" : "params",
            "context" : "ss: <mark>params<\/mark>",
            "weight" : 1,
            "pos" : 194 },
          
          { "form" : "params",
            "context" : "ss: <mark>params<\/mark>",
            "weight" : 1,
            "pos" : 333 },
          
          { "form" : "params",
            "context" : "ss: <mark>params<\/mark>",
            "weight" : 1,
            "pos" : 372 },
          
          { "form" : "params",
            "context" : "ss: <mark>params<\/mark>",
            "weight" : 1,
            "pos" : 416 },
          
          { "form" : "params",
            "context" : "ss: <mark>params<\/mark>",
            "weight" : 1,
            "pos" : 453 },
          
          { "form" : "params",
            "context" : "ss: <mark>params<\/mark>",
            "weight" : 1,
            "pos" : 490 },
          
          { "form" : "params",
            "context" : "<<mark>params<\/mark>> (Element containing most of the settings which...",
            "weight" : 1,
            "pos" : 502 },
          
          { "form" : "params",
            "context" : "ss: <mark>params<\/mark>",
            "weight" : 1,
            "pos" : 575 },
          
          { "form" : "params",
            "context" : "ss: <mark>params<\/mark>",
            "weight" : 1,
            "pos" : 604 },
          
          { "form" : "params",
            "context" : "ss: <mark>params<\/mark>",
            "weight" : 1,
            "pos" : 740 },
          
          { "form" : "params",
            "context" : "ss: <mark>params<\/mark>",
            "weight" : 1,
            "pos" : 798 },
          
          { "form" : "params",
            "context" : "ss: <mark>params<\/mark>",
            "weight" : 1,
            "pos" : 829 },
          
          { "form" : "params",
            "context" : "ss: <mark>params<\/mark>",
            "weight" : 1,
            "pos" : 858 },
          
          { "form" : "params",
            "context" : "ss: <mark>params<\/mark>",
            "weight" : 1,
            "pos" : 908 } ] },
      
      { "docId" : "howDoIUseIt",
        "docUri" : "howDoIUseIt.html",
        "score" : 3,
        "contexts" : 
        [ 
          { "form" : "params",
            "context" : "<<mark>params<\/mark>>",
            "weight" : 1,
            "pos" : 478 },
          
          { "form" : "params",
            "context" : "Only the <<mark>params<\/mark>> element is necessary, but, as we discuss...",
            "weight" : 1,
            "pos" : 481 },
          
          { "form" : "params",
            "context" : "The <<mark>params<\/mark>> element has two required elements for determining...",
            "weight" : 1,
            "pos" : 501 } ] } ] }